nose_title_print_example/__init__.py
nose_title_print_example/nose_title_print.py
nose_title_print_example-0.0.1.dist-info/LICENSE
nose_title_print_example-0.0.1.dist-info/METADATA
nose_title_print_example-0.0.1.dist-info/WHEEL
nose_title_print_example-0.0.1.dist-info/entry_points.txt
nose_title_print_example-0.0.1.dist-info/top_level.txt
nose_title_print_example-0.0.1.dist-info/RECORD
