Metadata-Version: 2.1
Name: nose_title_print_example
Version: 0.0.1
Summary: A small example package for nose test frame to print test title.
Author-email: yujianming <y2469464342@outlook.com>
Project-URL: Homepage, https://github.com/HEtinto/nose_title_print
Project-URL: Issues, https://github.com/HEtinto/nose_title_print
Classifier: Programming Language :: Python :: 3
Classifier: License :: OSI Approved :: MIT License
Classifier: Operating System :: OS Independent
Requires-Python: >=3.9
License-File: LICENSE
